!lab1/DMUX1to16.vhd
library IEEE;
use IEEE.STD_LOGIC_1164.all;

entity DMUX1to16 is
  port (
    D : in std_logic;
    S : in std_logic_vector(3 downto 0);
    Y : out std_logic_vector(15 downto 0)
  );
end DMUX1to16;

architecture GateLevel of DMUX1to16 is
begin

  Y(0) <= D and (not S(3)) and (not S(2)) and (not S(1)) and (not S(0)); -- 0000
  Y(1) <= D and (not S(3)) and (not S(2)) and (not S(1)) and S(0);
  Y(2) <= D and (not S(3)) and (not S(2)) and S(1) and (not S(0));
  Y(3) <= D and (not S(3)) and (not S(2)) and S(1) and S(0);

  Y(4) <= D and (not S(3)) and S(2) and (not S(1)) and (not S(0));
  Y(5) <= D and (not S(3)) and S(2) and (not S(1)) and S(0);
  Y(6) <= D and (not S(3)) and S(2) and S(1) and (not S(0));
  Y(7) <= D and (not S(3)) and S(2) and S(1) and S(0);

  Y(8)  <= D and S(3) and (not S(2)) and (not S(1)) and (not S(0));
  Y(9)  <= D and S(3) and (not S(2)) and (not S(1)) and S(0);
  Y(10) <= D and S(3) and (not S(2)) and S(1) and (not S(0));
  Y(11) <= D and S(3) and (not S(2)) and S(1) and S(0);

  Y(12) <= D and S(3) and S(2) and (not S(1)) and (not S(0));
  Y(13) <= D and S(3) and S(2) and (not S(1)) and S(0);
  Y(14) <= D and S(3) and S(2) and S(1) and (not S(0));
  Y(15) <= D and S(3) and S(2) and S(1) and S(0); -- 1111

end GateLevel;

!lab1/tb_DMUX1to16.vhd
library IEEE;
use IEEE.STD_LOGIC_1164.ALL;

entity tb_DMUX1to16 is
end tb_DMUX1to16;

architecture sim of tb_DMUX1to16 is

    signal D : STD_LOGIC := '0';
    signal S : STD_LOGIC_VECTOR(3 downto 0);

    signal Y : STD_LOGIC_VECTOR(15 downto 0);

    -- แยกออกมาเพื่อดูทีละเส้นใน GTKWave
    signal Y0  : STD_LOGIC;
    signal Y1  : STD_LOGIC;
    signal Y2  : STD_LOGIC;
    signal Y3  : STD_LOGIC;
    signal Y4  : STD_LOGIC;
    signal Y5  : STD_LOGIC;
    signal Y6  : STD_LOGIC;
    signal Y7  : STD_LOGIC;
    signal Y8  : STD_LOGIC;
    signal Y9  : STD_LOGIC;
    signal Y10 : STD_LOGIC;
    signal Y11 : STD_LOGIC;
    signal Y12 : STD_LOGIC;
    signal Y13 : STD_LOGIC;
    signal Y14 : STD_LOGIC;
    signal Y15 : STD_LOGIC;

begin

    uut : entity work.DMUX1to16
    port map (
        D => D,
        S => S,
        Y => Y
    );

    -- แตก Bus ออกเป็นรายบิต
    Y0  <= Y(0);
    Y1  <= Y(1);
    Y2  <= Y(2);
    Y3  <= Y(3);
    Y4  <= Y(4);
    Y5  <= Y(5);
    Y6  <= Y(6);
    Y7  <= Y(7);
    Y8  <= Y(8);
    Y9  <= Y(9);
    Y10 <= Y(10);
    Y11 <= Y(11);
    Y12 <= Y(12);
    Y13 <= Y(13);
    Y14 <= Y(14);
    Y15 <= Y(15);

    process
    begin

        D <= '1';

        S <= "0000"; wait for 10 ns;
        S <= "0001"; wait for 10 ns;
        S <= "0010"; wait for 10 ns;
        S <= "0011"; wait for 10 ns;

        S <= "0100"; wait for 10 ns;
        S <= "0101"; wait for 10 ns;
        S <= "0110"; wait for 10 ns;
        S <= "0111"; wait for 10 ns;

        S <= "1000"; wait for 10 ns;
        S <= "1001"; wait for 10 ns;
        S <= "1010"; wait for 10 ns;
        S <= "1011"; wait for 10 ns;

        S <= "1100"; wait for 10 ns;
        S <= "1101"; wait for 10 ns;
        S <= "1110"; wait for 10 ns;
        S <= "1111"; wait for 10 ns;

        D <= '0';

        wait;

    end process;

end sim;

!lab1/dmux.vcd
$date
  Thu Jul 16 23:51:58 2026
$end
$version
  GHDL v0
$end
$timescale
  1 fs
$end
$scope module standard $end
$upscope $end
$scope module std_logic_1164 $end
$upscope $end
$scope module tb_dmux1to16 $end
$var reg 1 ! d $end
$var reg 4 " s[3:0] $end
$var reg 16 # y[15:0] $end
$var reg 1 $ y0 $end
$var reg 1 % y1 $end
$var reg 1 & y2 $end
$var reg 1 ' y3 $end
$var reg 1 ( y4 $end
$var reg 1 ) y5 $end
$var reg 1 * y6 $end
$var reg 1 + y7 $end
$var reg 1 , y8 $end
$var reg 1 - y9 $end
$var reg 1 . y10 $end
$var reg 1 / y11 $end
$var reg 1 0 y12 $end
$var reg 1 1 y13 $end
$var reg 1 2 y14 $end
$var reg 1 3 y15 $end
$scope module uut $end
$var reg 1 4 d $end
$var reg 4 5 s[3:0] $end
$var reg 16 6 y[15:0] $end
$upscope $end
$upscope $end
$enddefinitions $end
#0
1!
b0000 "
b0000000000000001 #
1$
0%
0&
0'
0(
0)
0*
0+
0,
0-
0.
0/
00
01
02
03
14
b0000 5
b0000000000000001 6
#10000000
b0001 "
b0000000000000010 #
0$
1%
b0001 5
b0000000000000010 6
#20000000
b0010 "
b0000000000000100 #
0%
1&
b0010 5
b0000000000000100 6
#30000000
b0011 "
b0000000000001000 #
0&
1'
b0011 5
b0000000000001000 6
#40000000
b0100 "
b0000000000010000 #
0'
1(
b0100 5
b0000000000010000 6
#50000000
b0101 "
b0000000000100000 #
0(
1)
b0101 5
b0000000000100000 6
#60000000
b0110 "
b0000000001000000 #
0)
1*
b0110 5
b0000000001000000 6
#70000000
b0111 "
b0000000010000000 #
0*
1+
b0111 5
b0000000010000000 6
#80000000
b1000 "
b0000000100000000 #
0+
1,
b1000 5
b0000000100000000 6
#90000000
b1001 "
b0000001000000000 #
0,
1-
b1001 5
b0000001000000000 6
#100000000
b1010 "
b0000010000000000 #
0-
1.
b1010 5
b0000010000000000 6
#110000000
b1011 "
b0000100000000000 #
0.
1/
b1011 5
b0000100000000000 6
#120000000
b1100 "
b0001000000000000 #
0/
10
b1100 5
b0001000000000000 6
#130000000
b1101 "
b0010000000000000 #
00
11
b1101 5
b0010000000000000 6
#140000000
b1110 "
b0100000000000000 #
01
12
b1110 5
b0100000000000000 6
#150000000
b1111 "
b1000000000000000 #
02
13
b1111 5
b1000000000000000 6
#160000000
0!
b0000000000000000 #
03
04
b0000000000000000 6
